[
  {
    "id": "6900",
    "name": "Turmoil",
    "types": [
      "Lightning",
      "Water"
    ],
    "cards": [
      {
        "id": "6095",
        "count": 4
      },
      {
        "id": "6039",
        "count": 3
      },
      {
        "id": "6004",
        "count": 1
      },
      {
        "id": "6096",
        "count": 2
      },
      {
        "id": "6086",
        "count": 3
      },
      {
        "id": "6007",
        "count": 1
      },
      {
        "id": "6080",
        "count": 3
      },
      {
        "id": "6028",
        "count": 1
      },
      {
        "id": "6072",
        "count": 4
      },
      {
        "id": "6038",
        "count": 2
      },
      {
        "id": "6108",
        "count": 3
      },
      {
        "id": "6110",
        "count": 3
      },
      {
        "id": "6106",
        "count": 2
      },
      {
        "id": "6107",
        "count": 2
      },
      {
        "id": "6105",
        "count": 2
      },
      {
        "id": "9109",
        "count": 12
      },
      {
        "id": "9111",
        "count": 12
      }
    ]
  },
  {
    "id": "6901",
    "name": "Lava",
    "types": [
      "Fighting",
      "Fire"
    ],
    "cards": [
      {
        "id": "6070",
        "count": 4
      },
      {
        "id": "6037",
        "count": 3
      },
      {
        "id": "6003",
        "count": 1
      },
      {
        "id": "6087",
        "count": 3
      },
      {
        "id": "6060",
        "count": 1
      },
      {
        "id": "6091",
        "count": 3
      },
      {
        "id": "6062",
        "count": 1
      },
      {
        "id": "6081",
        "count": 3
      },
      {
        "id": "6059",
        "count": 1
      },
      {
        "id": "6084",
        "count": 2
      },
      {
        "id": "6089",
        "count": 2
      },
      {
        "id": "6103",
        "count": 1
      },
      {
        "id": "6108",
        "count": 3
      },
      {
        "id": "6110",
        "count": 3
      },
      {
        "id": "6107",
        "count": 2
      },
      {
        "id": "6101",
        "count": 3
      },
      {
        "id": "9107",
        "count": 14
      },
      {
        "id": "9106",
        "count": 10
      }
    ]
  }
]